sbuuid/__init__.py
sbuuid-0.2.1.dist-info/METADATA
sbuuid-0.2.1.dist-info/WHEEL
sbuuid-0.2.1.dist-info/top_level.txt
sbuuid-0.2.1.dist-info/RECORD
