Metadata-Version: 2.1
Name: sbuuid
Version: 0.2.1
Summary: A package to generate globally unique IDs
Home-page: https://github.com/shouvikbj/
Author: Shouvik Bajpayee
Author-email: shouvikbajpayee.private@gmail.com
Classifier: Programming Language :: Python :: 3
Classifier: License :: OSI Approved :: MIT License
Requires-Python: >=3.6
